{
  "id": "1385",
  "text": "Через постійні ворожі обстріли та наслідки попередніх масованих ракетно-дронових атак по Черкаській області 1 лютого за командою НЕК «Укренерго» застосовуватимуться графіки погодинних вимкнень (ГПВ). Години відсутності електропостачання: 1.1: 00:30 – 04:00, 06:00 – 10:00, 12:00 – 16:00, 18:00 – 22:00 1.2: 01:30 – 05:30, 07:30 – 11:30, 13:30 – 17:30, 19:30 – 22:30 2.1: 00:00 – 00:30, 03:00 – 06:30, 08:30 – 12:30, 14:30 – 18:30, 20:30 – 00:00 2.2: 00:00 – 01:30, 04:00 – 07:30, 09:30 – 13:30, 15:30 – 19:30, 21:30 – 00:00 3.1: 00:00 – 02:30, 05:00 – 08:30, 10:30 – 14:30, 16:30 – 20:00, 22:30 – 00:00 3.2: 00:00 – 01:00, 03:30 – 07:30, 09:30 – 13:30, 15:30 – 19:30, 21:30 – 00:00 4.1: 02:30 – 06:00, 08:00 – 12:00, 14:00 – 18:00, 20:00 – 23:30 4.2: 00:00 – 03:00, 05:30 – 09:30, 11:30 – 15:30, 17:30 – 21:30, 23:30 – 00:00 5.1: 00:00 – 02:00, 04:30 – 08:00, 10:00 – 14:00, 16:00 – 20:00, 22:00 – 00:00 5.2: 02:00 – 05:00, 07:30 – 11:30, 13:30 – 17:30, 19:30 – 23:30 6.1: 01:00 – 04:30, 06:30 – 10:30, 12:30 – 16:30, 18:30 – 22:00 6.2: 00:00 – 03:30, 06:00 – 09:30, 11:30 – 15:30, 17:30 – 21:30, 23:30 – 00:00 Перелік адрес, що знеструмлюються по чергах (підчергах) ГПВ можна переглянути за посиланням https://www.cherkasyoblenergo.com/off Зверніть увагу, ситуація в енергосистемі може змінюватися, тому стежте за нашими оновленнями.",
  "rawText": "Через постійні ворожі обстріли та наслідки попередніх масованих ракетно-дронових атак по Черкаській області 1 лютого за командою НЕК «Укренерго» застосовуватимуться графіки погодинних вимкнень (ГПВ).\n\nГодини відсутності електропостачання:\n\n1.1: 00:30 – 04:00, 06:00 – 10:00, 12:00 – 16:00, 18:00 – 22:00\n\n1.2: 01:30 – 05:30, 07:30 – 11:30, 13:30 – 17:30, 19:30 – 22:30\n\n2.1: 00:00 – 00:30, 03:00 – 06:30, 08:30 – 12:30, 14:30 – 18:30, 20:30 – 00:00\n\n2.2: 00:00 – 01:30, 04:00 – 07:30, 09:30 – 13:30, 15:30 – 19:30, 21:30 – 00:00\n\n3.1: 00:00 – 02:30, 05:00 – 08:30, 10:30 – 14:30, 16:30 – 20:00, 22:30 – 00:00\n\n3.2: 00:00 – 01:00, 03:30 – 07:30, 09:30 – 13:30, 15:30 – 19:30, 21:30 – 00:00\n\n4.1: 02:30 – 06:00, 08:00 – 12:00, 14:00 – 18:00, 20:00 – 23:30\n\n4.2: 00:00 – 03:00, 05:30 – 09:30, 11:30 – 15:30, 17:30 – 21:30, 23:30 – 00:00\n\n5.1: 00:00 – 02:00, 04:30 – 08:00, 10:00 – 14:00, 16:00 – 20:00, 22:00 – 00:00\n\n5.2: 02:00 – 05:00, 07:30 – 11:30, 13:30 – 17:30, 19:30 – 23:30\n\n6.1: 01:00 – 04:30, 06:30 – 10:30, 12:30 – 16:30, 18:30 – 22:00\n\n6.2: 00:00 – 03:30, 06:00 – 09:30, 11:30 – 15:30, 17:30 – 21:30, 23:30 – 00:00\n\nПерелік адрес, що знеструмлюються по чергах (підчергах) ГПВ можна переглянути за посиланням https://www.cherkasyoblenergo.com/off\n\nЗверніть увагу, ситуація в енергосистемі може змінюватися, тому стежте за нашими оновленнями.",
  "date": "2026-01-31T19:49:14+00:00",
  "url": "https://t.me/pat_cherkasyoblenergo/1385",
  "schedule": [
    {
      "queue": "1.1",
      "ranges": [
        "00:30-04:00",
        "06:00-10:00",
        "12:00-16:00",
        "18:00-22:00"
      ]
    },
    {
      "queue": "1.2",
      "ranges": [
        "01:30-05:30",
        "07:30-11:30",
        "13:30-17:30",
        "19:30-22:30"
      ]
    },
    {
      "queue": "2.1",
      "ranges": [
        "00:00-00:30",
        "03:00-06:30",
        "08:30-12:30",
        "14:30-18:30",
        "20:30-24:00"
      ]
    },
    {
      "queue": "2.2",
      "ranges": [
        "00:00-01:30",
        "04:00-07:30",
        "09:30-13:30",
        "15:30-19:30",
        "21:30-24:00"
      ]
    },
    {
      "queue": "3.1",
      "ranges": [
        "00:00-02:30",
        "05:00-08:30",
        "10:30-14:30",
        "16:30-20:00",
        "22:30-24:00"
      ]
    },
    {
      "queue": "3.2",
      "ranges": [
        "00:00-01:00",
        "03:30-07:30",
        "09:30-13:30",
        "15:30-19:30",
        "21:30-24:00"
      ]
    },
    {
      "queue": "4.1",
      "ranges": [
        "02:30-06:00",
        "08:00-12:00",
        "14:00-18:00",
        "20:00-23:30"
      ]
    },
    {
      "queue": "4.2",
      "ranges": [
        "00:00-03:00",
        "05:30-09:30",
        "11:30-15:30",
        "17:30-21:30",
        "23:30-24:00"
      ]
    },
    {
      "queue": "5.1",
      "ranges": [
        "00:00-02:00",
        "04:30-08:00",
        "10:00-14:00",
        "16:00-20:00",
        "22:00-24:00"
      ]
    },
    {
      "queue": "5.2",
      "ranges": [
        "02:00-05:00",
        "07:30-11:30",
        "13:30-17:30",
        "19:30-23:30"
      ]
    },
    {
      "queue": "6.1",
      "ranges": [
        "01:00-04:30",
        "06:30-10:30",
        "12:30-16:30",
        "18:30-22:00"
      ]
    },
    {
      "queue": "6.2",
      "ranges": [
        "00:00-03:30",
        "06:00-09:30",
        "11:30-15:30",
        "17:30-21:30",
        "23:30-24:00"
      ]
    }
  ],
  "scheduleDateText": "1 лютого",
  "scheduleDateIso": "2026-02-01",
  "contentHash": "4151cb42b84d1abfb3617d557f01cd78cdfe1f37908b30e00d540783d23c49e2"
}